LICENSE
MANIFEST.in
README.rst
setup.cfg
setup.py
django_simple_api_auth/__init__.py
django_simple_api_auth/admin.py
django_simple_api_auth/apps.py
django_simple_api_auth/errors.py
django_simple_api_auth/models.py
django_simple_api_auth/tests.py
django_simple_api_auth/views.py
django_simple_api_auth.egg-info/PKG-INFO
django_simple_api_auth.egg-info/SOURCES.txt
django_simple_api_auth.egg-info/dependency_links.txt
django_simple_api_auth.egg-info/requires.txt
django_simple_api_auth.egg-info/top_level.txt
django_simple_api_auth/api/__init__.py
django_simple_api_auth/api/graphql/__init__.py
django_simple_api_auth/api/graphql/ariadne/__init__.py
django_simple_api_auth/api/graphql/ariadne/mixins.py
django_simple_api_auth/api/graphql/ariadne/mutations.py
django_simple_api_auth/api/graphql/ariadne/queries.py
django_simple_api_auth/api/graphql/graphene/__init__.py
django_simple_api_auth/api/graphql/graphene/mutations.py
django_simple_api_auth/api/graphql/graphene/queries.py
django_simple_api_auth/api/graphql/graphene/types.py
django_simple_api_auth/api/rest/__init__.py
django_simple_api_auth/api/rest/v1_0/__init__.py
django_simple_api_auth/api/rest/v1_0/mixins.py
django_simple_api_auth/api/rest/v1_0/serializers.py
django_simple_api_auth/api/rest/v1_0/viewsets.py
django_simple_api_auth/business_logic/__init__.py
django_simple_api_auth/business_logic/user_create.py
django_simple_api_auth/business_logic/user_login.py
django_simple_api_auth/business_logic/user_logout.py
django_simple_api_auth/business_logic/user_password_recovery.py
django_simple_api_auth/business_logic/user_reset_password.py
django_simple_api_auth/business_logic/user_social_login.py
django_simple_api_auth/migrations/__init__.py
django_simple_api_auth/templates/__init__.py
django_simple_api_auth/templates/emails/base.html
django_simple_api_auth/templates/emails/password_recovery/email.html
django_simple_api_auth/templates/emails/password_recovery/subject.txt
django_simple_api_auth/utils/__init__.py
django_simple_api_auth/utils/rest/__init__.py
django_simple_api_auth/utils/rest/viewsets/__init__.py
django_simple_api_auth/utils/rest/viewsets/views.py
example/__init__.py
example/manage.py
example/common/__init__.py
