Metadata-Version: 2.1
Name: django-simple-api-auth
Version: 0.0.2
Summary: Django Simple Api Auth is a Django app to help developers with the Session auth of a rest or graphql api in Django.
Home-page: https://github.com/mrmilu/django-simple-api-auth-example
Author: p02diada
Author-email: p02diada@gmail.com
License: MIT
Platform: UNKNOWN
Classifier: Environment :: Web Environment
Classifier: Framework :: Django
Classifier: Framework :: Django :: 3.2
Classifier: Intended Audience :: Developers
Classifier: License :: OSI Approved :: MIT License
Classifier: Operating System :: OS Independent
Classifier: Programming Language :: Python
Classifier: Programming Language :: Python :: 3
Classifier: Programming Language :: Python :: 3 :: Only
Classifier: Programming Language :: Python :: 3.6
Classifier: Programming Language :: Python :: 3.7
Classifier: Programming Language :: Python :: 3.8
Classifier: Topic :: Internet :: WWW/HTTP
Classifier: Topic :: Internet :: WWW/HTTP :: Dynamic Content
Requires-Python: >=3.9
Provides-Extra: test
Provides-Extra: dev
License-File: LICENSE
